sqlmemo/__init__.py
sqlmemo/schema.py
sqlmemo/serialize.py
sqlmemo/sqlmemo.py
sqlmemo-0.3.1.dist-info/LICENSE
sqlmemo-0.3.1.dist-info/METADATA
sqlmemo-0.3.1.dist-info/WHEEL
sqlmemo-0.3.1.dist-info/RECORD
