Metadata-Version: 2.1
Name: sqlmemo
Version: 0.3.1
Summary: Memoizing SQL-backed Computation Cache
Home-page: https://github.com/gavento/sqlmemo
License: MIT
Keywords: memoization,cache,sql
Author: Tomas Gavenciak
Author-email: gavento@gmail.com
Requires-Python: >=3.10,<4.0
Classifier: License :: OSI Approved :: MIT License
Classifier: Programming Language :: Python :: 3
Classifier: Programming Language :: Python :: 3.10
Classifier: Programming Language :: Python :: 3.11
Classifier: Programming Language :: Python :: 3.12
Classifier: Programming Language :: Python :: 3.13
Provides-Extra: dill
Requires-Dist: dill (>=0.3.9,<0.4.0) ; extra == "dill"
Requires-Dist: sqlalchemy (>=2.0.30,<3.0.0)
Project-URL: Repository, https://github.com/gavento/sqlmemo
